{
    "root": [
        {
            "type": "1",
            "name": "ebook",
            "url": "",
            "children": [
                {
                    "type": "1",
                    "name": "408",
                    "url": "",
                    "children": [
                        {
                            "type": "1",
                            "name": "co",
                            "url": "",
                            "children": []
                        },
                        {
                            "type": "1",
                            "name": "ds",
                            "url": "",
                            "children": []
                        },
                        {
                            "type": "1",
                            "name": "net",
                            "url": "",
                            "children": []
                        },
                        {
                            "type": "1",
                            "name": "os",
                            "url": "",
                            "children": []
                        }
                    ]
                }
            ]
        }
    ]
}